[{"city": "Bogota", "lat": 4.6126, "lng": -74.0705}, {"city": "Timbio", "lat": 2.3528, "lng": -76.6819}, {"city": "Medellin", "lat": 6.2447, "lng": -75.5748}, {"city": "Cali", "lat": 3.44, "lng": -76.5197}, {"city": "Barranquilla", "lat": 10.9639, "lng": -74.7964}, {"city": "Cartagena", "lat": 10.4236, "lng": -75.5253}, {"city": "Palermo", "lat": 2.8883, "lng": -75.4339}, {"city": "Cucuta", "lat": 7.9075, "lng": -72.5047}, {"city": "Soledad", "lat": 10.92, "lng": -74.77}, {"city": "Pereira", "lat": 4.8143, "lng": -75.6946}, {"city": "Bucaramanga", "lat": 7.1186, "lng": -73.1161}, {"city": "Valledupar", "lat": 10.4603, "lng": -73.2597}, {"city": "Ibague", "lat": 4.4378, "lng": -75.2006}, {"city": "Villavicencio", "lat": 4.1425, "lng": -73.6294}, {"city": "Soacha", "lat": 4.5781, "lng": -74.2144}, {"city": "Santa Marta", "lat": 11.2361, "lng": -74.2017}, {"city": "Monteria", "lat": 8.76, "lng": -75.8856}, {"city": "Manizales", "lat": 5.0661, "lng": -75.4847}, {"city": "Buenaventura", "lat": 3.8772, "lng": -77.0267}, {"city": "Pasto", "lat": 1.21, "lng": -77.2747}, {"city": "Bello", "lat": 6.3319, "lng": -75.5581}, {"city": "Neiva", "lat": 2.9275, "lng": -75.2875}, {"city": "Palmira", "lat": 3.5347, "lng": -76.2956}, {"city": "Zarzal", "lat": 4.3942, "lng": -76.0703}, {"city": "Armenia", "lat": 4.5389, "lng": -75.6725}, {"city": "Popayan", "lat": 2.4411, "lng": -76.6061}, {"city": "Itagui", "lat": 6.1726, "lng": -75.6096}, {"city": "Sincelejo", "lat": 9.2994, "lng": -75.3958}, {"city": "Floridablanca", "lat": 7.0697, "lng": -73.0978}, {"city": "Envigado", "lat": 6.1719, "lng": -75.5803}, {"city": "Tulua", "lat": 4.0847, "lng": -76.1986}, {"city": "Tunja", "lat": 5.5403, "lng": -73.3614}, {"city": "Barrancabermeja", "lat": 7.0675, "lng": -73.8472}, {"city": "Zipaquira", "lat": 5.0247, "lng": -74.0014}, {"city": "Dosquebradas", "lat": 4.8361, "lng": -75.6761}, {"city": "Turbo", "lat": 8.0931, "lng": -76.7283}, {"city": "Riohacha", "lat": 11.5442, "lng": -72.9069}, {"city": "Giron", "lat": 7.0731, "lng": -73.1681}, {"city": "Florencia", "lat": 1.6142, "lng": -75.6117}, {"city": "Fusagasuga", "lat": 4.3372, "lng": -74.3644}, {"city": "Rionegro", "lat": 6.1533, "lng": -75.3742}, {"city": "Cartago", "lat": 4.75, "lng": -75.91}, {"city": "Pitalito", "lat": 1.8539, "lng": -76.0514}, {"city": "Quibdo", "lat": 5.6923, "lng": -76.6582}, {"city": "Girardot", "lat": 4.3036, "lng": -74.8039}, {"city": "Cienaga", "lat": 11.0067, "lng": -74.2467}, {"city": "Duitama", "lat": 5.8219, "lng": -73.0297}, {"city": "Magangue", "lat": 9.2467, "lng": -74.7594}, {"city": "Maicao", "lat": 11.3778, "lng": -72.2414}, {"city": "Apartado", "lat": 7.8847, "lng": -76.635}, {"city": "Uribia", "lat": 11.7139, "lng": -72.2658}, {"city": "Piedecuesta", "lat": 6.9886, "lng": -73.0503}, {"city": "Facatativa", "lat": 4.8147, "lng": -74.3553}, {"city": "Guadalajara de Buga", "lat": 3.9036, "lng": -76.2986}, {"city": "Santander de Quilichao", "lat": 3.0083, "lng": -76.4839}, {"city": "Sogamoso", "lat": 5.7143, "lng": -72.9339}, {"city": "Madrid", "lat": 4.7306, "lng": -74.2639}, {"city": "Aguachica", "lat": 8.3067, "lng": -73.6153}, {"city": "Ipiales", "lat": 0.8289, "lng": -77.6406}, {"city": "Yopal", "lat": 5.3306, "lng": -72.3906}, {"city": "Arauca", "lat": 7.0903, "lng": -70.7617}, {"city": "Sabaneta", "lat": 6.1508, "lng": -75.615}, {"city": "San Andres", "lat": 12.5847, "lng": -81.7006}, {"city": "San Jose del Guaviare", "lat": 2.5653, "lng": -72.6386}, {"city": "Leticia", "lat": -4.215, "lng": -69.9411}, {"city": "Mitu", "lat": 1.2503, "lng": -70.235}, {"city": "Mocoa", "lat": 1.1492, "lng": -76.6464}, {"city": "Inirida", "lat": 3.8708, "lng": -67.9211}, {"city": "Puerto Carreno", "lat": 6.1889, "lng": -67.4858}, {"city": "Chia", "lat": 4.8633, "lng": -74.0528}, {"city": "Jamundi", "lat": 3.2608, "lng": -76.5394}, {"city": "Yumbo", "lat": 3.5778, "lng": -76.4944}, {"city": "Mosquera", "lat": 4.7078, "lng": -74.2328}, {"city": "Fundacion", "lat": 10.5172, "lng": -74.1922}, {"city": "Ocana", "lat": 8.2461, "lng": -73.3553}, {"city": "Montelibano", "lat": 7.9711, "lng": -75.4181}, {"city": "Tumaco", "lat": 1.81, "lng": -78.81}, {"city": "Chiquinquira", "lat": 5.6175, "lng": -73.8164}, {"city": "Sabanalarga", "lat": 10.63, "lng": -74.9236}, {"city": "Chigorodo", "lat": 7.6697, "lng": -76.6814}, {"city": "Cerete", "lat": 8.8867, "lng": -75.7911}, {"city": "Funza", "lat": 4.7175, "lng": -74.2094}, {"city": "Caldas", "lat": 6.0886, "lng": -75.6361}, {"city": "Los Patios", "lat": 7.8342, "lng": -72.505}, {"city": "Tierralta", "lat": 8.1728, "lng": -76.0594}, {"city": "Arjona", "lat": 10.255, "lng": -75.3447}, {"city": "Espinal", "lat": 4.1486, "lng": -74.8819}, {"city": "Acacias", "lat": 3.9889, "lng": -73.7647}, {"city": "Copacabana", "lat": 6.3486, "lng": -75.5103}, {"city": "Santa Rosa de Cabal", "lat": 4.8672, "lng": -75.6211}, {"city": "La Dorada", "lat": 5.4538, "lng": -74.6647}, {"city": "San Vicente del Caguan", "lat": 2.1153, "lng": -74.77}, {"city": "Corozal", "lat": 9.3169, "lng": -75.2933}, {"city": "Villa del Rosario", "lat": 7.8353, "lng": -72.4736}, {"city": "Garzon", "lat": 2.1961, "lng": -75.6292}, {"city": "Planeta Rica", "lat": 8.4089, "lng": -75.5819}, {"city": "Necocli", "lat": 8.4258, "lng": -76.7839}, {"city": "Manaure", "lat": 11.775, "lng": -72.4444}, {"city": "El Carmen de Bolivar", "lat": 9.7183, "lng": -75.1225}, {"city": "Marinilla", "lat": 6.1744, "lng": -75.3389}, {"city": "Cienaga de Oro", "lat": 8.875, "lng": -75.6211}, {"city": "Turbaco", "lat": 10.3319, "lng": -75.4142}, {"city": "Puerto Asis", "lat": 0.5006, "lng": -76.4989}, {"city": "Riosucio", "lat": 5.4208, "lng": -75.7028}, {"city": "Plato", "lat": 9.7925, "lng": -74.7825}, {"city": "Villamaria", "lat": 5.0456, "lng": -75.5153}, {"city": "San Marcos", "lat": 8.6622, "lng": -75.1289}, {"city": "Pamplona", "lat": 7.3761, "lng": -72.6483}, {"city": "Florida", "lat": 3.3217, "lng": -76.2347}, {"city": "Pradera", "lat": 3.4189, "lng": -76.2439}, {"city": "Orito", "lat": 0.6661, "lng": -76.8708}, {"city": "Riosucio", "lat": 7.4386, "lng": -77.1133}, {"city": "Puerto Boyaca", "lat": 5.9761, "lng": -74.5875}, {"city": "El Banco", "lat": 9.0008, "lng": -73.9744}, {"city": "San Gil", "lat": 6.555, "lng": -73.1336}, {"city": "Valle del Guamuez", "lat": 0.4253, "lng": -76.9053}, {"city": "Puerto Libertador", "lat": 7.8881, "lng": -75.6717}, {"city": "Barbosa", "lat": 6.4375, "lng": -75.3306}, {"city": "Tame", "lat": 6.4583, "lng": -71.7447}, {"city": "Lorica", "lat": 9.2419, "lng": -75.816}, {"city": "Girardota", "lat": 6.3769, "lng": -75.4461}, {"city": "San Onofre", "lat": 9.7372, "lng": -75.5256}, {"city": "El Bagre", "lat": 7.6047, "lng": -74.8086}, {"city": "Guarne", "lat": 6.2792, "lng": -75.4419}, {"city": "Baranoa", "lat": 10.7956, "lng": -74.9194}, {"city": "Chinu", "lat": 9.1097, "lng": -75.3981}, {"city": "Cimitarra", "lat": 6.3133, "lng": -73.95}, {"city": "Maria la Baja", "lat": 9.9811, "lng": -75.2986}, {"city": "Samaniego", "lat": 1.3364, "lng": -77.5925}, {"city": "Agustin Codazzi", "lat": 10.0367, "lng": -73.2369}, {"city": "Carepa", "lat": 7.7581, "lng": -76.6553}, {"city": "La Vega", "lat": 2.0008, "lng": -76.7778}, {"city": "San Andres de Sotavento", "lat": 9.1453, "lng": -75.5086}, {"city": "Chaparral", "lat": 3.7236, "lng": -75.4847}, {"city": "Ayapel", "lat": 8.3125, "lng": -75.145}, {"city": "Urrao", "lat": 6.3156, "lng": -76.1342}, {"city": "Roldanillo", "lat": 4.4136, "lng": -76.1547}, {"city": "Valencia", "lat": 8.2592, "lng": -76.1469}, {"city": "Puerto Tejada", "lat": 3.23, "lng": -76.4175}, {"city": "Cajica", "lat": 4.9167, "lng": -74.025}, {"city": "San Pelayo", "lat": 8.9578, "lng": -75.8375}, {"city": "Arboletes", "lat": 8.8511, "lng": -76.4272}, {"city": "Villeta", "lat": 5.0128, "lng": -74.4731}, {"city": "Andes", "lat": 5.6556, "lng": -75.8803}, {"city": "Aguazul", "lat": 5.1689, "lng": -72.5467}, {"city": "Cumaribo", "lat": 4.4461, "lng": -69.7956}, {"city": "Miranda", "lat": 3.2503, "lng": -76.2286}, {"city": "El Charco", "lat": 2.4775, "lng": -78.1111}, {"city": "Montenegro", "lat": 4.5653, "lng": -75.7511}, {"city": "Caceres", "lat": 7.5794, "lng": -75.3503}, {"city": "Santa Rosa del Sur", "lat": 7.9633, "lng": -74.0533}, {"city": "Pueblo Nuevo", "lat": 8.505, "lng": -75.5075}, {"city": "Tuchin", "lat": 9.1858, "lng": -75.5553}, {"city": "Yarumal", "lat": 6.9633, "lng": -75.4172}, {"city": "Arauquita", "lat": 7.0261, "lng": -71.4272}, {"city": "Guaduas", "lat": 5.0694, "lng": -74.5981}, {"city": "Segovia", "lat": 7.0781, "lng": -74.7017}, {"city": "Pie de Pato", "lat": 5.5153, "lng": -76.9747}, {"city": "La Union", "lat": 4.5331, "lng": -76.1006}, {"city": "Cumbal", "lat": 0.9078, "lng": -77.7908}, {"city": "Aracataca", "lat": 10.5911, "lng": -74.185}, {"city": "Tuquerres", "lat": 1.0872, "lng": -77.6189}, {"city": "Acevedo", "lat": 1.8047, "lng": -75.8897}, {"city": "Villa de San Diego de Ubate", "lat": 5.3072, "lng": -73.8144}, {"city": "Libano", "lat": 4.9206, "lng": -75.0611}, {"city": "Bosconia", "lat": 9.9761, "lng": -73.8903}, {"city": "San Juan del Cesar", "lat": 10.7708, "lng": -73.0031}, {"city": "Puerto Berrio", "lat": 6.4906, "lng": -74.4047}, {"city": "Taraza", "lat": 7.5839, "lng": -75.4003}, {"city": "Cajibio", "lat": 2.6233, "lng": -76.5731}, {"city": "Sibate", "lat": 4.4908, "lng": -74.2594}, {"city": "Sampues", "lat": 9.1847, "lng": -75.3786}, {"city": "Dibulla", "lat": 11.2725, "lng": -73.3089}, {"city": "El Bordo", "lat": 2.1142, "lng": -76.9831}, {"city": "Santa Rosa de Osos", "lat": 6.6472, "lng": -75.4606}, {"city": "Melgar", "lat": 4.2039, "lng": -74.6428}, {"city": "Tibu", "lat": 8.64, "lng": -72.7381}, {"city": "Dagua", "lat": 3.6575, "lng": -76.6917}, {"city": "La Macarena", "lat": 2.1828, "lng": -73.7847}, {"city": "Belalcazar", "lat": 2.6469, "lng": -75.9717}, {"city": "Tocancipa", "lat": 4.9661, "lng": -73.9111}, {"city": "Sonson", "lat": 5.7094, "lng": -75.3106}, {"city": "San Pablo", "lat": 7.4764, "lng": -73.9231}, {"city": "San Bernardo del Viento", "lat": 9.355, "lng": -75.9544}, {"city": "Guacari", "lat": 3.7647, "lng": -76.3322}, {"city": "Santiago de Tolu", "lat": 9.525, "lng": -75.5817}, {"city": "Gigante", "lat": 2.3867, "lng": -75.5461}, {"city": "Quimbaya", "lat": 4.6239, "lng": -75.7631}, {"city": "Cartagena del Chaira", "lat": 1.3361, "lng": -74.8467}, {"city": "Yarumal", "lat": 7.0306, "lng": -75.5905}, {"city": "Fonseca", "lat": 10.8858, "lng": -72.8481}, {"city": "San Vicente de Chucuri", "lat": 6.8819, "lng": -73.4119}, {"city": "San Luis de Since", "lat": 9.2447, "lng": -75.1458}, {"city": "Puerto Lopez", "lat": 4.0897, "lng": -72.9619}, {"city": "Campoalegre", "lat": 2.6867, "lng": -75.3256}, {"city": "Buenos Aires", "lat": 3.0164, "lng": -76.6411}, {"city": "Caldono", "lat": 2.7969, "lng": -76.4828}, {"city": "Quinchia", "lat": 5.3394, "lng": -75.7294}, {"city": "San Agustin", "lat": 1.8792, "lng": -76.2683}, {"city": "San Juan Nepomuceno", "lat": 9.9522, "lng": -75.0811}, {"city": "Majagual", "lat": 8.5408, "lng": -74.6297}, {"city": "Puerto Rico", "lat": 1.9075, "lng": -75.1583}, {"city": "San Antero", "lat": 9.3775, "lng": -75.7603}, {"city": "Corinto", "lat": 3.1739, "lng": -76.2594}, {"city": "La Virginia", "lat": 4.8967, "lng": -75.8839}, {"city": "Pivijay", "lat": 10.4608, "lng": -74.6153}, {"city": "Puebloviejo", "lat": 10.9942, "lng": -74.2833}, {"city": "Puerto Escondido", "lat": 9.0192, "lng": -76.2614}, {"city": "Bocas de Satinga", "lat": 2.3469, "lng": -78.3256}, {"city": "Silvia", "lat": 2.6108, "lng": -76.3789}, {"city": "El Dificil", "lat": 9.8469, "lng": -74.2367}, {"city": "Inza", "lat": 2.5503, "lng": -76.0636}, {"city": "San Pedro de Uraba", "lat": 8.275, "lng": -76.3769}, {"city": "Remedios", "lat": 7.0275, "lng": -74.6939}, {"city": "Paipa", "lat": 5.78, "lng": -73.1175}, {"city": "Galapa", "lat": 10.9003, "lng": -74.8853}, {"city": "Guachaves", "lat": 1.2219, "lng": -77.6772}, {"city": "Sitionuevo", "lat": 10.7758, "lng": -74.7203}, {"city": "Puerto Wilches", "lat": 7.3483, "lng": -73.8983}, {"city": "Neira", "lat": 5.1664, "lng": -75.5189}, {"city": "Guamo", "lat": 4.0281, "lng": -74.97}, {"city": "Amaga", "lat": 6.0383, "lng": -75.7028}, {"city": "Chimichagua", "lat": 9.2578, "lng": -73.8133}, {"city": "Planadas", "lat": 3.1964, "lng": -75.6444}, {"city": "Tabio", "lat": 4.9158, "lng": -74.0983}, {"city": "Barbosa", "lat": 5.9331, "lng": -73.6147}, {"city": "Fresno", "lat": 5.1536, "lng": -75.0369}, {"city": "Purificacion", "lat": 3.8567, "lng": -74.9325}, {"city": "Flandes", "lat": 4.2844, "lng": -74.8142}, {"city": "Sopo", "lat": 4.9081, "lng": -73.9403}, {"city": "Monitos", "lat": 9.2461, "lng": -76.1286}, {"city": "Aipe", "lat": 3.2219, "lng": -75.2375}, {"city": "La Dorada", "lat": 0.3436, "lng": -76.9108}, {"city": "La Calera", "lat": 4.7197, "lng": -73.97}, {"city": "Caicedonia", "lat": 4.3347, "lng": -75.8281}, {"city": "Hatonuevo", "lat": 11.0672, "lng": -72.7631}, {"city": "San Carlos", "lat": 8.7944, "lng": -75.6994}, {"city": "Isnos", "lat": 1.9289, "lng": -76.2158}, {"city": "Coyaima", "lat": 3.7975, "lng": -75.1939}, {"city": "Circasia", "lat": 4.62, "lng": -75.6347}, {"city": "Guamal", "lat": 9.1442, "lng": -74.2236}, {"city": "Supia", "lat": 5.4506, "lng": -75.6514}, {"city": "Argelia", "lat": 2.2558, "lng": -77.2492}, {"city": "Ciudad Bolivar", "lat": 5.8494, "lng": -76.0203}, {"city": "San Juan de Uraba", "lat": 8.7611, "lng": -76.5286}, {"city": "Tauramena", "lat": 5.0167, "lng": -72.75}, {"city": "Pueblo Bello", "lat": 10.4164, "lng": -73.5867}, {"city": "Puerto Colombia", "lat": 10.9922, "lng": -74.9528}, {"city": "Fortul", "lat": 6.7931, "lng": -71.7714}, {"city": "Los Cordobas", "lat": 8.8953, "lng": -76.3547}, {"city": "Morales", "lat": 2.7603, "lng": -76.6339}, {"city": "San Benito Abad", "lat": 8.9272, "lng": -75.0264}, {"city": "San Alberto", "lat": 7.7592, "lng": -73.3931}, {"city": "Balboa", "lat": 2.0406, "lng": -77.2164}, {"city": "Pensilvania", "lat": 5.384, "lng": -75.1612}, {"city": "Buesaco", "lat": 1.3847, "lng": -77.1564}, {"city": "Paz de Ariporo", "lat": 5.8811, "lng": -71.8917}, {"city": "Mahates", "lat": 10.2322, "lng": -75.1911}, {"city": "Istmina", "lat": 5.1633, "lng": -76.6867}, {"city": "Santa Ana", "lat": 9.3194, "lng": -74.5706}, {"city": "San Martin", "lat": 3.6969, "lng": -73.6986}, {"city": "Nechi", "lat": 8.0958, "lng": -74.775}, {"city": "Pinillos", "lat": 8.915, "lng": -74.4619}, {"city": "Yolombo", "lat": 6.5978, "lng": -75.0122}, {"city": "Solano", "lat": 0.6983, "lng": -75.2539}, {"city": "Sandona", "lat": 1.2847, "lng": -77.4711}, {"city": "Vistahermosa", "lat": 3.1239, "lng": -73.7514}, {"city": "Sabanagrande", "lat": 10.7903, "lng": -74.7556}, {"city": "San Jose", "lat": 1.6967, "lng": -78.2453}, {"city": "La Union", "lat": 1.6053, "lng": -77.1297}, {"city": "Choconta", "lat": 5.1467, "lng": -73.6825}, {"city": "Socorro", "lat": 6.4603, "lng": -73.27}, {"city": "Santa Rosa", "lat": 10.4456, "lng": -75.3686}, {"city": "Villanueva", "lat": 4.6087, "lng": -72.9288}, {"city": "Algeciras", "lat": 2.5219, "lng": -75.3144}, {"city": "Calamar", "lat": 10.25, "lng": -74.9158}, {"city": "Valdivia", "lat": 7.1636, "lng": -75.4392}, {"city": "El Retorno", "lat": 2.3306, "lng": -72.6278}, {"city": "Puerto Guzman", "lat": 0.9636, "lng": -76.4086}, {"city": "La Montanita", "lat": 1.4792, "lng": -75.4361}, {"city": "Donmatias", "lat": 6.4858, "lng": -75.3953}, {"city": "Cogua", "lat": 5.0619, "lng": -73.9794}, {"city": "Marsella", "lat": 4.9367, "lng": -75.7392}, {"city": "Rioblanco", "lat": 3.5292, "lng": -75.6447}, {"city": "El Zulia", "lat": 7.9325, "lng": -72.6025}, {"city": "Honda", "lat": 5.2069, "lng": -74.7367}, {"city": "San Jose", "lat": 1.4739, "lng": -77.0808}, {"city": "Canalete", "lat": 8.79, "lng": -76.2411}, {"city": "Alcala", "lat": 4.6736, "lng": -75.7825}, {"city": "El Paso", "lat": 9.6622, "lng": -73.7519}, {"city": "Santo Tomas", "lat": 10.7575, "lng": -74.7558}, {"city": "Teorama", "lat": 8.4353, "lng": -73.2864}, {"city": "Palmar de Varela", "lat": 10.7389, "lng": -74.7547}, {"city": "Puerto Concordia", "lat": 2.6233, "lng": -72.7592}, {"city": "Achi", "lat": 8.5692, "lng": -74.5561}, {"city": "Curumani", "lat": 9.1997, "lng": -73.5425}, {"city": "Guadalupe", "lat": 2.025, "lng": -75.7564}, {"city": "Luruaco", "lat": 10.6083, "lng": -75.1417}, {"city": "Dabeiba", "lat": 7.0014, "lng": -76.2611}, {"city": "Santa Fe de Antioquia", "lat": 6.5564, "lng": -75.8275}, {"city": "Buenavista", "lat": 8.2233, "lng": -75.4817}, {"city": "Amalfi", "lat": 6.9092, "lng": -75.0767}, {"city": "Manzanares", "lat": 5.2519, "lng": -75.1569}, {"city": "Sardinata", "lat": 8.0836, "lng": -72.8003}, {"city": "Mutata", "lat": 7.2433, "lng": -76.4358}, {"city": "El Colegio", "lat": 4.5808, "lng": -74.4425}, {"city": "La Jagua de Ibirico", "lat": 9.5611, "lng": -73.3364}, {"city": "Natagaima", "lat": 3.6231, "lng": -75.0936}, {"city": "El Doncello", "lat": 1.68, "lng": -75.285}, {"city": "Repelon", "lat": 10.4944, "lng": -75.1242}, {"city": "Silvania", "lat": 4.4033, "lng": -74.3881}, {"city": "Pailitas", "lat": 8.9597, "lng": -73.625}, {"city": "Villa de Leyva", "lat": 5.6331, "lng": -73.5256}, {"city": "Timbiqui", "lat": 2.7719, "lng": -77.665}, {"city": "Tiquisio", "lat": 8.5578, "lng": -74.2639}, {"city": "Taminango", "lat": 1.57, "lng": -77.2806}, {"city": "Ginebra", "lat": 3.7244, "lng": -76.2672}, {"city": "Puerto Triunfo", "lat": 5.8728, "lng": -74.6397}, {"city": "San Bernardo", "lat": 1.5164, "lng": -77.0467}, {"city": "San Jacinto", "lat": 9.8311, "lng": -75.1219}, {"city": "Nueva Granada", "lat": 9.8011, "lng": -74.3917}, {"city": "Galeras", "lat": 9.1586, "lng": -75.0489}, {"city": "Santa Barbara", "lat": 5.8747, "lng": -75.5661}, {"city": "Villagarzon", "lat": 1.0294, "lng": -76.6164}, {"city": "Moniquira", "lat": 5.8744, "lng": -73.5717}, {"city": "Almaguer", "lat": 1.9131, "lng": -76.8561}, {"city": "El Paujil", "lat": 1.5694, "lng": -75.3264}, {"city": "Aguadas", "lat": 5.6092, "lng": -75.4564}, {"city": "Montecristo", "lat": 8.2958, "lng": -74.4728}, {"city": "Suaza", "lat": 1.975, "lng": -75.7956}, {"city": "Villapinzon", "lat": 5.2158, "lng": -73.5967}, {"city": "Fredonia", "lat": 5.9267, "lng": -75.6739}, {"city": "El Reten", "lat": 10.6106, "lng": -74.2683}, {"city": "Bugalagrande", "lat": 4.2075, "lng": -76.1575}, {"city": "Samaca", "lat": 5.4919, "lng": -73.4867}, {"city": "Ovejas", "lat": 9.5258, "lng": -75.2272}, {"city": "Sotomayor", "lat": 1.4933, "lng": -77.5214}, {"city": "Timana", "lat": 1.9499, "lng": -75.9139}, {"city": "San Lorenzo", "lat": 1.5039, "lng": -77.2178}, {"city": "Tenjo", "lat": 4.8697, "lng": -74.1439}, {"city": "Concordia", "lat": 6.0456, "lng": -75.9075}, {"city": "Simiti", "lat": 7.9564, "lng": -73.9461}, {"city": "Rovira", "lat": 4.2392, "lng": -75.2403}, {"city": "Polonuevo", "lat": 10.7772, "lng": -74.8528}, {"city": "Urumita", "lat": 10.5603, "lng": -73.0136}, {"city": "La Union", "lat": 5.9728, "lng": -75.3611}, {"city": "Tado", "lat": 5.2633, "lng": -76.56}, {"city": "Velez", "lat": 6.0131, "lng": -73.6736}, {"city": "Tocaima", "lat": 4.4578, "lng": -74.6347}, {"city": "Campo de la Cruz", "lat": 10.3778, "lng": -74.8814}, {"city": "Ponedera", "lat": 10.6419, "lng": -74.7531}, {"city": "Sabana de Torres", "lat": 7.3903, "lng": -73.5003}, {"city": "Pelaya", "lat": 8.6892, "lng": -73.6653}, {"city": "Salgar", "lat": 5.9639, "lng": -75.9775}, {"city": "Totoro", "lat": 2.5103, "lng": -76.4019}, {"city": "La Primavera", "lat": 5.4906, "lng": -70.4092}, {"city": "Guaranda", "lat": 8.4672, "lng": -74.5367}, {"city": "El Rosal", "lat": 4.8519, "lng": -74.2628}, {"city": "Suesca", "lat": 5.1017, "lng": -73.7981}, {"city": "Betulia", "lat": 6.1122, "lng": -75.9839}, {"city": "Retiro", "lat": 6.0597, "lng": -75.5039}, {"city": "El Pinon", "lat": 10.4039, "lng": -74.8231}, {"city": "Anori", "lat": 7.0736, "lng": -75.1469}, {"city": "Aquitania", "lat": 5.5194, "lng": -72.8836}, {"city": "Chivolo", "lat": 10.0264, "lng": -74.6214}, {"city": "Guasca", "lat": 4.8658, "lng": -73.8772}, {"city": "Landazuri", "lat": 6.2181, "lng": -73.8114}, {"city": "Tamesis", "lat": 5.6647, "lng": -75.7144}, {"city": "La Apartada", "lat": 8.05, "lng": -75.3356}, {"city": "Obando", "lat": 4.5761, "lng": -75.9731}, {"city": "Condoto", "lat": 5.0917, "lng": -76.65}, {"city": "Anapoima", "lat": 4.5503, "lng": -74.5361}, {"city": "Sopetran", "lat": 6.5017, "lng": -75.7433}, {"city": "Tenerife", "lat": 9.8989, "lng": -74.8589}, {"city": "Juan de Acosta", "lat": 10.8286, "lng": -75.035}, {"city": "Titiribi", "lat": 6.0625, "lng": -75.7936}, {"city": "Rio de Oro", "lat": 8.2917, "lng": -73.3872}, {"city": "El Carmen de Atrato", "lat": 5.8983, "lng": -76.1431}, {"city": "Cordoba", "lat": 0.8533, "lng": -77.5178}, {"city": "Guapi", "lat": 2.5604, "lng": -77.86}, {"city": "Jardin", "lat": 5.5983, "lng": -75.8197}, {"city": "Filandia", "lat": 4.6733, "lng": -75.6583}, {"city": "Altos del Rosario", "lat": 8.7914, "lng": -74.1636}, {"city": "Manati", "lat": 10.4481, "lng": -74.9592}, {"city": "San Jacinto del Cauca", "lat": 8.2497, "lng": -74.72}, {"city": "Rosas", "lat": 2.26, "lng": -76.74}, {"city": "Anolaima", "lat": 4.7633, "lng": -74.4647}, {"city": "Los Santos", "lat": 6.7561, "lng": -73.1022}, {"city": "Santa Barbara de Pinto", "lat": 9.4353, "lng": -74.7017}, {"city": "Saboya", "lat": 5.6969, "lng": -73.7631}, {"city": "Hatillo de Loba", "lat": 8.9556, "lng": -74.0769}, {"city": "Cordoba", "lat": 9.5867, "lng": -74.8272}, {"city": "Ebejico", "lat": 6.3264, "lng": -75.7661}, {"city": "Curiti", "lat": 6.6044, "lng": -73.0681}, {"city": "Caimito", "lat": 8.7894, "lng": -75.1161}, {"city": "Oiba", "lat": 6.2639, "lng": -73.2992}, {"city": "Santa Lucia", "lat": 10.3247, "lng": -74.9589}, {"city": "Cisneros", "lat": 6.5383, "lng": -75.0886}, {"city": "Puente Nacional", "lat": 5.8772, "lng": -73.6786}, {"city": "Candelaria", "lat": 10.4592, "lng": -74.8806}, {"city": "La Union", "lat": 8.8572, "lng": -75.2767}, {"city": "Guayabal", "lat": 5.0306, "lng": -74.8844}, {"city": "Covenas", "lat": 9.4014, "lng": -75.68}, {"city": "Talaigua Nuevo", "lat": 9.3028, "lng": -74.5678}, {"city": "El Playon", "lat": 7.4703, "lng": -73.2033}, {"city": "Agua de Dios", "lat": 4.3781, "lng": -74.6683}, {"city": "El Aguila", "lat": 4.9081, "lng": -76.0422}, {"city": "Belen de los Andaquies", "lat": 1.4164, "lng": -75.8727}, {"city": "El Tarra", "lat": 8.5756, "lng": -73.0944}, {"city": "Mogotes", "lat": 6.4764, "lng": -72.9703}, {"city": "Santo Domingo", "lat": 6.4708, "lng": -75.1658}, {"city": "Tubara", "lat": 10.8742, "lng": -74.9786}, {"city": "Regidor", "lat": 8.6664, "lng": -73.8222}, {"city": "Lenguazaque", "lat": 5.3069, "lng": -73.7117}, {"city": "Charala", "lat": 6.2875, "lng": -73.1467}, {"city": "Medina", "lat": 4.5092, "lng": -73.3494}, {"city": "Granada", "lat": 6.1442, "lng": -75.1853}, {"city": "Suaita", "lat": 6.1019, "lng": -73.4406}, {"city": "Margarita", "lat": 9.1531, "lng": -74.2881}, {"city": "Norosi", "lat": 8.5261, "lng": -74.0378}, {"city": "Puerto Narino", "lat": -3.7703, "lng": -70.3831}, {"city": "Chita", "lat": 6.1878, "lng": -72.4725}, {"city": "Granada", "lat": 4.5186, "lng": -74.3514}, {"city": "Pesca", "lat": 5.5589, "lng": -73.0503}, {"city": "Tibana", "lat": 5.3172, "lng": -73.3969}, {"city": "San Zenon", "lat": 9.245, "lng": -74.4992}, {"city": "Guatape", "lat": 6.2325, "lng": -75.1586}, {"city": "Nuqui", "lat": 5.7069, "lng": -77.2703}, {"city": "Alvarado", "lat": 4.5672, "lng": -74.9533}, {"city": "Bojaca", "lat": 4.7336, "lng": -74.3422}, {"city": "Iles", "lat": 0.9706, "lng": -77.5208}, {"city": "Zapatoca", "lat": 6.815, "lng": -73.2683}, {"city": "Junin", "lat": 4.7903, "lng": -73.6633}, {"city": "Usiacuri", "lat": 10.7428, "lng": -74.9758}, {"city": "La Belleza", "lat": 5.8575, "lng": -73.9656}, {"city": "Muzo", "lat": 5.5297, "lng": -74.1044}, {"city": "Orocue", "lat": 4.7897, "lng": -71.3392}, {"city": "Puerres", "lat": 0.8839, "lng": -77.5039}, {"city": "Aratoca", "lat": 6.6956, "lng": -73.0175}, {"city": "San Francisco", "lat": 4.9711, "lng": -74.2892}, {"city": "Uramita", "lat": 6.8986, "lng": -76.1736}, {"city": "Motavita", "lat": 5.5772, "lng": -73.3672}, {"city": "Uribe", "lat": 3.2408, "lng": -74.3536}, {"city": "Pedraza", "lat": 10.1886, "lng": -74.9156}, {"city": "Puerto Parra", "lat": 6.6514, "lng": -74.0569}, {"city": "San Luis de Palenque", "lat": 5.4222, "lng": -71.7314}, {"city": "Paratebueno", "lat": 4.3753, "lng": -73.2131}, {"city": "Santana", "lat": 6.0572, "lng": -73.4811}, {"city": "Coromoro", "lat": 6.295, "lng": -73.0406}, {"city": "Tarso", "lat": 5.865, "lng": -75.8225}, {"city": "Ambalema", "lat": 4.7817, "lng": -74.7639}, {"city": "Maripi", "lat": 5.5489, "lng": -74.0067}, {"city": "Simacota", "lat": 6.4431, "lng": -73.3375}, {"city": "Soata", "lat": 6.3328, "lng": -72.6839}, {"city": "Tona", "lat": 7.2019, "lng": -72.9664}, {"city": "Socha", "lat": 5.9978, "lng": -72.6922}, {"city": "Boavita", "lat": 6.3308, "lng": -72.5842}, {"city": "Salento", "lat": 4.6372, "lng": -75.5708}, {"city": "Guatavita", "lat": 4.9344, "lng": -73.8344}, {"city": "Guican", "lat": 6.4625, "lng": -72.4119}, {"city": "Cubara", "lat": 7.0008, "lng": -72.1081}, {"city": "Albania", "lat": 1.3289, "lng": -75.8783}, {"city": "Tasco", "lat": 5.9092, "lng": -72.7814}, {"city": "Florian", "lat": 5.8028, "lng": -73.9714}, {"city": "Heliconia", "lat": 6.2106, "lng": -75.73}, {"city": "Alban", "lat": 4.8783, "lng": -74.4383}, {"city": "Coloso", "lat": 9.4942, "lng": -75.3525}, {"city": "Sutamarchan", "lat": 5.6206, "lng": -73.6214}, {"city": "Chitaraque", "lat": 6.0283, "lng": -73.4469}, {"city": "Zipacon", "lat": 4.76, "lng": -74.3797}, {"city": "Villanueva", "lat": 6.6719, "lng": -73.1747}, {"city": "Chiquiza", "lat": 5.61, "lng": -73.4889}, {"city": "Caramanta", "lat": 5.5467, "lng": -75.6442}, {"city": "Tota", "lat": 5.5603, "lng": -72.9861}, {"city": "Cordoba", "lat": 4.3911, "lng": -75.6878}, {"city": "San Jose de Pare", "lat": 6.0192, "lng": -73.5467}, {"city": "Arcabuco", "lat": 5.7544, "lng": -73.4375}, {"city": "El Cocuy", "lat": 6.4094, "lng": -72.4444}, {"city": "Betulia", "lat": 6.9, "lng": -73.2836}, {"city": "Labranzagrande", "lat": 5.5633, "lng": -72.5775}, {"city": "Jurado", "lat": 7.1114, "lng": -77.7714}]